rbcde/__init__.py
rbcde/matrix.py
rbcde-1.0.0.dist-info/LICENSE
rbcde-1.0.0.dist-info/METADATA
rbcde-1.0.0.dist-info/WHEEL
rbcde-1.0.0.dist-info/top_level.txt
rbcde-1.0.0.dist-info/RECORD
